safe_cli/__init__.py
safe_cli/argparse_validators.py
safe_cli/ethereum_hd_wallet.py
safe_cli/main.py
safe_cli/prompt_parser.py
safe_cli/safe_addresses.py
safe_cli/safe_cli.py
safe_cli/safe_completer.py
safe_cli/safe_completer_constants.py
safe_cli/safe_creator.py
safe_cli/safe_lexer.py
safe_cli/typer_validators.py
safe_cli/utils.py
safe_cli/contracts/__init__.py
safe_cli/contracts/safe_to_l2_migration.py
safe_cli/operators/__init__.py
safe_cli/operators/enums.py
safe_cli/operators/exceptions.py
safe_cli/operators/safe_operator.py
safe_cli/operators/safe_tx_service_operator.py
safe_cli/operators/hw_wallets/__init__.py
safe_cli/operators/hw_wallets/constants.py
safe_cli/operators/hw_wallets/exceptions.py
safe_cli/operators/hw_wallets/hw_wallet.py
safe_cli/operators/hw_wallets/hw_wallet_manager.py
safe_cli/operators/hw_wallets/ledger_exceptions.py
safe_cli/operators/hw_wallets/ledger_wallet.py
safe_cli/operators/hw_wallets/trezor_exceptions.py
safe_cli/operators/hw_wallets/trezor_wallet.py
safe_cli/tx_builder/__init__.py
safe_cli/tx_builder/exceptions.py
safe_cli/tx_builder/tx_builder_file_decoder.py
safe_cli-1.8.0.dist-info/METADATA
safe_cli-1.8.0.dist-info/WHEEL
safe_cli-1.8.0.dist-info/entry_points.txt
safe_cli-1.8.0.dist-info/licenses/LICENSE
safe_cli-1.8.0.dist-info/RECORD
