Metadata-Version: 2.4
Name: safe-cli
Version: 1.8.0
Summary: Command Line Interface for Safe
Project-URL: Download, https://github.com/gnosis/safe-cli/releases
Project-URL: Homepage, https://github.com/gnosis/safe-cli
Author-email: Uxío Fuentefría <uxio@safe.global>
License-Expression: MIT
License-File: LICENSE
Classifier: License :: OSI Approved :: MIT License
Classifier: Operating System :: OS Independent
Classifier: Programming Language :: Python
Classifier: Programming Language :: Python :: 3.10
Classifier: Programming Language :: Python :: 3.11
Classifier: Programming Language :: Python :: 3.12
Classifier: Programming Language :: Python :: 3.13
Requires-Python: >=3.8
Requires-Dist: art>=6
Requires-Dist: colorama>=0.4
Requires-Dist: hexbytes>1
Requires-Dist: prompt-toolkit>=3
Requires-Dist: pygments>=2
Requires-Dist: requests>=2
Requires-Dist: safe-eth-py>=7
Requires-Dist: tabulate>=0.8
Requires-Dist: typer>=0.14.0
Provides-Extra: ledger
Requires-Dist: ledgereth==0.10.0; extra == 'ledger'
Provides-Extra: trezor
Requires-Dist: trezor==0.13.10; extra == 'trezor'
